CHANGES.rst
LICENSE
MANIFEST.in
README.rst
distribute_setup.py
setup.py
restorm/__init__.py
restorm/conf.py
restorm/exceptions.py
restorm/resource.py
restorm/rest.py
restorm/utils.py
restorm/clients/__init__.py
restorm/clients/base.py
restorm/clients/jsonclient.py
restorm/clients/mockclient.py
restorm/clients/xmlclient.py
restorm/clients/tests/__init__.py
restorm/clients/tests/test_jsonclient.py
restorm/clients/tests/test_mockclient.py
restorm/examples/__init__.py
restorm/examples/flickr/__init__.py
restorm/examples/flickr/api.py
restorm/examples/flickr/settings_local_example.py
restorm/examples/flickr/tests.py
restorm/examples/mock/__init__.py
restorm/examples/mock/api.py
restorm/examples/mock/library_serv.py
restorm/examples/mock/ticket_serv.py
restorm/examples/twitter/__init__.py
restorm/examples/twitter/api.py
restorm/examples/twitter/settings_local_example.py
restorm/examples/twitter/tests.py
restorm/tests/__init__.py
restorm/tests/test_resource.py
restorm/tests/test_rest.py
restorm_setuptools.egg-info/PKG-INFO
restorm_setuptools.egg-info/SOURCES.txt
restorm_setuptools.egg-info/dependency_links.txt
restorm_setuptools.egg-info/not-zip-safe
restorm_setuptools.egg-info/requires.txt
restorm_setuptools.egg-info/top_level.txt