Metadata-Version: 1.1
Name: restorm-setuptools
Version: 0.3.1
Summary: RestORM allows you to interact with resources as if they were objects.
Home-page: http://github.com/goinnn/restorm
Author: Joeri Bekker
Author-email: joeri@maykinmedia.nl
License: MIT
Platform: any
Classifier: Development Status :: 4 - Beta
Classifier: Intended Audience :: Developers
Classifier: Intended Audience :: System Administrators
Classifier: License :: OSI Approved :: MIT License
Classifier: Operating System :: OS Independent
Classifier: Programming Language :: Python
Classifier: Topic :: Software Development
